chrphb_friends/__init__.py
chrphb_friends/_modidx.py
chrphb_friends/core.py
chrphb_friends-0.0.1.dist-info/LICENSE
chrphb_friends-0.0.1.dist-info/METADATA
chrphb_friends-0.0.1.dist-info/WHEEL
chrphb_friends-0.0.1.dist-info/entry_points.txt
chrphb_friends-0.0.1.dist-info/top_level.txt
chrphb_friends-0.0.1.dist-info/RECORD
